GauChkParser_.cp313-win_amd64.pyd
GauChkParser/ChkReader.py
GauChkParser/Constants.py
GauChkParser/Types.py
GauChkParser/__init__.py
gauchkparser-0.1.23.dist-info/METADATA
gauchkparser-0.1.23.dist-info/WHEEL
gauchkparser-0.1.23.dist-info/top_level.txt
gauchkparser-0.1.23.dist-info/RECORD
