Metadata-Version: 2.1
Name: GauChkParser
Version: 0.1.23
Summary: A parser for Gaussian .chk format
Author: YujieLiu
Author-email: 
Classifier: Programming Language :: Python
Classifier: Programming Language :: Python :: 3
Classifier: Programming Language :: C++
Requires-Python: >=3.8
Requires-Dist: numpy
